tk_rest/__init__.py
tk_rest/tk_rest.py
tk_rest-0.1.7.dist-info/LICENSE.txt
tk_rest-0.1.7.dist-info/METADATA
tk_rest-0.1.7.dist-info/RECORD
tk_rest-0.1.7.dist-info/WHEEL
tk_rest-0.1.7.dist-info/top_level.txt
