Metadata-Version: 2.1
Name: tk-rest
Version: 0.1.7
Summary: Explore REST API in a heartbeat
Home-page: https://github.com/qhuydtvt/tk-rest
Author: TechKids Coding School
Author-email: techkidsvn@gmail.com
License: UNKNOWN
Platform: UNKNOWN
Classifier: Programming Language :: Python :: 3
Classifier: License :: OSI Approved :: MIT License
Classifier: Operating System :: OS Independent
Requires-Dist: requests
